credly/__init__.py
credly/client.py
credly/exceptions.py
credly/http.py
credly/resources/__init__.py
credly/resources/authorization_tokens.py
credly/resources/badge_templates.py
credly/resources/badges.py
credly/resources/base.py
credly/resources/employees.py
credly/resources/issuer_authorizations.py
credly/resources/organizations.py
credly_python_api-0.2.0.dist-info/licenses/LICENSE
tests/__init__.py
tests/conftest.py
tests/test_client.py
tests/test_exceptions.py
tests/test_http.py
tests/test_resources.py
credly_python_api-0.2.0.dist-info/METADATA
credly_python_api-0.2.0.dist-info/WHEEL
credly_python_api-0.2.0.dist-info/top_level.txt
credly_python_api-0.2.0.dist-info/RECORD
